moduflow/__init__.py
moduflow/__main__.py
moduflow/cli/__init__.py
moduflow/cli/commands.py
moduflow/cli/main.py
moduflow/compilers/__init__.py
moduflow/compilers/project.py
moduflow/compilers/section.py
moduflow/core/__init__.py
moduflow/core/config.py
moduflow/core/exceptions.py
moduflow/core/paths.py
moduflow/handlers/__init__.py
moduflow/handlers/file_handler.py
moduflow/handlers/section_handler.py
moduflow/handlers/yaml_handler.py
moduflow/prompts/__init__.py
moduflow/prompts/templates.py
moduflow/utils/__init__.py
moduflow/utils/helpers.py
moduflow-0.1.3.dist-info/LICENSE
moduflow-0.1.3.dist-info/METADATA
moduflow-0.1.3.dist-info/WHEEL
moduflow-0.1.3.dist-info/entry_points.txt
moduflow-0.1.3.dist-info/top_level.txt
moduflow-0.1.3.dist-info/RECORD
