Metadata-Version: 2.2
Name: moduflow
Version: 0.1.3
Summary: Section-based development with Test-Driven Development support
Author: "Brian Onang'o"
Author-email: Brian Onang'o <surgbc@gmail.com>
License: MIT
Project-URL: Homepage, https://github.com/example/moduflow
Project-URL: Bug Tracker, https://github.com/example/moduflow/issues
Keywords: development,tdd,modular,sections
Classifier: Development Status :: 3 - Alpha
Classifier: Intended Audience :: Developers
Classifier: License :: OSI Approved :: MIT License
Classifier: Programming Language :: Python :: 3
Classifier: Programming Language :: Python :: 3.7
Classifier: Programming Language :: Python :: 3.8
Classifier: Programming Language :: Python :: 3.9
Classifier: Programming Language :: Python :: 3.10
Classifier: Topic :: Software Development :: Build Tools
Requires-Python: >=3.7
License-File: LICENSE
Requires-Dist: pyyaml>=6.0
Requires-Dist: click>=8.0.0
Provides-Extra: docs
Requires-Dist: sphinx>=5.0.0; extra == "docs"
Requires-Dist: sphinx-rtd-theme; extra == "docs"
